headroom/__init__.py
headroom/config.yaml
headroom/first_run.py
headroom/max.py
headroom/max_display.py
headroom/system_tools.py
headroom/tool_registry.py
headroom/tools.py
headroom/user_preferences.py
headroom/utils.py
headroom/assets/Max_Logo.png
headroom/assets/Max_Logo_ASCII.txt
headroom/assets/Max_Logo_orange.png
headroom-0.2.7.dist-info/licenses/LICENSE
headroom-0.2.7.dist-info/METADATA
headroom-0.2.7.dist-info/WHEEL
headroom-0.2.7.dist-info/entry_points.txt
headroom-0.2.7.dist-info/top_level.txt
headroom-0.2.7.dist-info/RECORD
