Metadata-Version: 2.4
Name: headroom
Version: 0.2.7
Summary: A powerful, extensible command-line AI assistant.
Author: James Bridges
License: MIT License
Project-URL: Homepage, https://github.com/SUNKENDREAMS/headroom
Project-URL: Bug Tracker, https://github.com/SUNKENDREAMS/headroom/issues
Keywords: ai,agent,cli,llm,automation,tools
Classifier: Development Status :: 4 - Beta
Classifier: Environment :: Console
Classifier: Intended Audience :: Developers
Classifier: Intended Audience :: System Administrators
Classifier: License :: OSI Approved :: MIT License
Classifier: Programming Language :: Python :: 3
Classifier: Programming Language :: Python :: 3.8
Classifier: Programming Language :: Python :: 3.9
Classifier: Programming Language :: Python :: 3.10
Classifier: Programming Language :: Python :: 3.11
Classifier: Programming Language :: Python :: 3.12
Classifier: Programming Language :: Python :: 3.13
Classifier: Topic :: Scientific/Engineering :: Artificial Intelligence
Classifier: Topic :: Utilities
License-File: LICENSE
Requires-Dist: prompt_toolkit
Requires-Dist: pygments
Requires-Dist: requests
Requires-Dist: pyyaml
Requires-Dist: python-dotenv
Requires-Dist: platformdirs
Dynamic: license-file
